nexoclom/.vscode/settings.json
nexoclom/__init__.py
nexoclom/atomicdata/__init__.py
nexoclom/atomicdata/atomicmass.py
nexoclom/atomicdata/g_values.py
nexoclom/atomicdata/initialize_atomicdata.py
nexoclom/atomicdata/photolossrates.py
nexoclom/data/InputFiles/Ca.fitted.input
nexoclom/data/InputFiles/Mg.fitted.input
nexoclom/data/InputFiles/Na.fitted.input
nexoclom/data/Loss/Photo/Berezhnoy2008.dat
nexoclom/data/Loss/Photo/Berezhnoy2013.dat
nexoclom/data/Loss/Photo/Huebner2011.dat
nexoclom/data/Loss/photorates.pkl
nexoclom/data/PlanetaryConstants.dat
nexoclom/data/PlanetaryConstants.pkl
nexoclom/data/SolarSystemContents.csv
nexoclom/data/bokeh.yml
nexoclom/data/g-values/C.Killen2009.dat
nexoclom/data/g-values/Ca+.Killen2009.dat
nexoclom/data/g-values/Ca.4227.KillenXXXX.dat
nexoclom/data/g-values/Ca.Killen2009.dat
nexoclom/data/g-values/Ca.Killen2009.dat.old
nexoclom/data/g-values/Ca_gval_50_354.txt
nexoclom/data/g-values/H.Killen2009.dat
nexoclom/data/g-values/He.Killen2009.dat
nexoclom/data/g-values/K.Killen2009.dat
nexoclom/data/g-values/Mg+.Killen2009.dat
nexoclom/data/g-values/Mg.Killen2009.dat.old
nexoclom/data/g-values/Mg.KillenXXXX.dat
nexoclom/data/g-values/Mn.KillenXXXX.dat
nexoclom/data/g-values/Na.3303.Killen2009.dat
nexoclom/data/g-values/Na.D1.KillenXXXX.dat
nexoclom/data/g-values/Na.D2.KillenXXXX.dat
nexoclom/data/g-values/O.Killen2009.dat
nexoclom/data/g-values/OH.Killen2009.dat
nexoclom/data/g-values/S.Killen2009.dat
nexoclom/data/g-values/Ti.KillenXXXX.dat
nexoclom/data/g-values/g-values.csv
nexoclom/data/g-values/g-values.pkl
nexoclom/data/naif_ids.dat
nexoclom/data/schema.sql
nexoclom/data/sso_query.sql
nexoclom/data_simulation/LOSResult.py
nexoclom/data_simulation/LOSResultFitted.py
nexoclom/data_simulation/LOSResultFitted_old.py
nexoclom/data_simulation/LOS_wrapper.py
nexoclom/data_simulation/ModelImage.py
nexoclom/data_simulation/ModelResult.py
nexoclom/data_simulation/__init__.py
nexoclom/data_simulation/compute_iteration.py
nexoclom-3.7.4.dist-info/LICENSE.rst
nexoclom-3.7.4.dist-info/LICENSES/LICENSE.rst
nexoclom-3.7.4.dist-info/LICENSES/README.rst
nexoclom-3.7.4.dist-info/LICENSES/TEMPLATE_LICENCE.rst
nexoclom-3.7.4.dist-info/METADATA
nexoclom-3.7.4.dist-info/WHEEL
nexoclom-3.7.4.dist-info/RECORD
