Metadata-Version: 2.1
Name: nexoclom
Version: 3.7.4
Summary: Neutral EXosphere and CLoud Model
License: BSD 3-Clause
Author: Matthew Burger
Author-email: mburger@stsci.edu
Requires-Python: >=3.10,<3.13
Classifier: License :: Other/Proprietary License
Classifier: Programming Language :: Python :: 3
Classifier: Programming Language :: Python :: 3.10
Classifier: Programming Language :: Python :: 3.11
Requires-Dist: SQLAlchemy (>=2.0.17,<3.0.0)
Requires-Dist: astropy (>=5.3,<6.0)
Requires-Dist: astroquery (>=0.4.6,<0.5.0)
Requires-Dist: bokeh (>=3.2.0,<4.0.0)
Requires-Dist: dash (>=2.11.0,<3.0.0)
Requires-Dist: dask[distributed] (>=2023.6.1,<2024.0.0)
Requires-Dist: ipython (>=8.14.0,<9.0.0)
Requires-Dist: matplotlib (>=3.7.1,<4.0.0)
Requires-Dist: numpy (>=1.25.0,<2.0.0)
Requires-Dist: pandas (>=1,<2)
Requires-Dist: periodictable (>=1.6.1,<2.0.0)
Requires-Dist: plotly (>=5.15.0,<6.0.0)
Requires-Dist: psycopg (>=3.1.9,<4.0.0)
Requires-Dist: pymongo (>=4.4.0,<5.0.0)
Requires-Dist: pytest (>=7.4.0,<8.0.0)
Requires-Dist: scikit-learn (>=1.2.2,<2.0.0)
Requires-Dist: scipy (>=1.11.1,<2.0.0)
Requires-Dist: selenium-firefox (>=2.0.8,<3.0.0)
Requires-Dist: spiceypy (>=5.1.2,<6.0.0)
Requires-Dist: twine (>=4.0.2,<5.0.0)
